{
    "debugMode": false,
    "heartbeat": {
        "intervalInHours": 3,
        "lastHeartbeatTime": ""
    },
    "notification": {
        "webEx": {
            "active": true,
            "webhooks": {
                "default": "https://webexapis.com/v1/webhooks/incoming/<secret-f54e7b098b>",
                "prod": "https://webexapis.com/v1/webhooks/incoming/<secret-f54e7b098b>",
                "test": "https://webexapis.com/v1/webhooks/incoming/<secret-f54e7b098b>"
            }
        },
        "msTeams": {
            "active": false,
            "webhooks": {
                "default": "",
                "prod": "",
                "test": ""
            }
        }
    }
}
